{
  "no_valid_id": [
    {
      "id": "",
      "label": "",
      "user_label": "connective tissue sheath",
      "row_number": 32
    }
  ],
  "no_found_id": [],
  "diff_label": [
    {
      "id": "UBERON:0002073",
      "label": "hair follicle",
      "asct_label": "hair follicle bulge",
      "user_label": "hair bulge",
      "row_number": 34
    },
    {
      "id": "UBERON:0002033",
      "label": "arrector muscle of hair",
      "asct_label": "arrector pili muscle of vibrissa",
      "user_label": "Arrector pili muscle",
      "row_number": 31
    },
    {
      "id": "CL:0000669",
      "label": "pericyte",
      "asct_label": "pericyte cell",
      "user_label": "Pericyte",
      "row_number": 66
    }
  ],
  "no_parent": []
}