{
  "no_valid_id": [
    {
      "id": "",
      "label": "",
      "user_label": "airway submucosal gland ciliated duct cell",
      "row_number": 13
    },
    {
      "id": "",
      "label": "",
      "user_label": "airway submucosal gland ciliated duct cells",
      "row_number": 31
    },
    {
      "id": "",
      "label": "",
      "user_label": "airway submucosal gland ciliated duct cells",
      "row_number": 51
    },
    {
      "id": "FMA:84472",
      "label": "pulmonary interlobular septum",
      "user_label": "pulmonary interlobular septum",
      "row_number": 101
    },
    {
      "id": "FMA:84472",
      "label": "pulmonary interlobular septum",
      "user_label": "pulmonary interlobular septum",
      "row_number": 102
    },
    {
      "id": "FMA:84472",
      "label": "pulmonary interlobular septum",
      "user_label": "pulmonary interlobular septum",
      "row_number": 103
    }
  ],
  "no_found_id": [],
  "diff_label": [],
  "no_parent": [
    {
      "id": "",
      "label": "",
      "user_label": "airway submucosal gland ciliated duct cell",
      "row_number": 13
    },
    {
      "id": "",
      "label": "",
      "user_label": "airway submucosal gland ciliated duct cells",
      "row_number": 31
    },
    {
      "id": "",
      "label": "",
      "user_label": "airway submucosal gland ciliated duct cells",
      "row_number": 51
    }
  ]
}